MANIFEST.in
README
README.md
setup.py
Pyganim.egg-info/PKG-INFO
Pyganim.egg-info/SOURCES.txt
Pyganim.egg-info/dependency_links.txt
Pyganim.egg-info/top_level.txt
docs/Makefile
docs/basics.rst
docs/conf.py
docs/index.rst
docs/install.rst
docs/make.bat
docs/transformations.rst
docs/unittests.rst
pyganim/__init__.py
tests/basicTests.py