Metadata-Version: 1.1
Name: Pyganim
Version: 0.9.2
Summary: A sprite animation module for Pygame.
Home-page: http://inventwithpython.com/pyganim
Author: Al Sweigart
Author-email: al@inventwithpython.com
License: BSD
Keywords: pygame sprite animation game 2D graphics
Platform: UNKNOWN
Classifier: Development Status :: 3 - Alpha
Classifier: Environment :: Win32 (MS Windows)
Classifier: Environment :: X11 Applications
Classifier: Environment :: MacOS X
Classifier: Intended Audience :: Developers
Classifier: License :: OSI Approved :: BSD License
Classifier: Operating System :: OS Independent
Classifier: Programming Language :: Python
Classifier: Programming Language :: Python :: 2
Classifier: Programming Language :: Python :: 2.7
Classifier: Programming Language :: Python :: 3
Classifier: Programming Language :: Python :: 3.3
Classifier: Programming Language :: Python :: 3.4
Classifier: Programming Language :: Python :: 3.5
